Metadata-Version: 2.1
Name: GuDory1
Version: 1.0.6
Summary: A simple package for https://app.tea.xyz/. Example GuDory1 - https://github.com/CryptoGu1/GuDory1.git and GuDory2 - https://github.com/CryptoGu1/GuDory2.git
Home-page: https://github.com/CryptoGu1/Dorytea1.git
Author: CryptoGu1
Author-email: Kriptoairdrop9@gmail.com
Project-URL: Homepage, https://github.com/CryptoGu1/GuDory1.git
Project-URL: Source, https://github.com/CryptoGu1/GuDory1.git
Classifier: License :: OSI Approved :: MIT License
Classifier: Programming Language :: Python :: 3
Requires-Python: >=3.6
Requires-Dist: requests>=2.20.0
Requires-Dist: GuDory2
